nbragg/__init__.py
nbragg/cross_section.py
nbragg/data.py
nbragg/models.py
nbragg/py.typed
nbragg/response.py
nbragg/utils.py
nbragg-0.6.0.dist-info/licenses/LICENSE
nbragg-0.6.0.dist-info/METADATA
nbragg-0.6.0.dist-info/WHEEL
nbragg-0.6.0.dist-info/top_level.txt
nbragg-0.6.0.dist-info/RECORD
