Metadata-Version: 2.4
Name: nbragg
Version: 0.6.0
Summary: Simple yet powerful package for neutron resonance fitting
Author-email: "Tsviki Y. Hirsh" <tsviki.hirsh@gmail.com>
Project-URL: Homepage, https://github.com/TsvikiHirsh/nbragg
Project-URL: Bug Tracker, https://github.com/TsvikiHirsh/nbragg/issues
Project-URL: Discussions, https://github.com/TsvikiHirsh/nbragg/discussions
Project-URL: Changelog, https://github.com/TsvikiHirsh/nbragg/releases
Classifier: Development Status :: 3 - Alpha
Classifier: Intended Audience :: Science/Research
Classifier: License :: OSI Approved :: MIT License
Classifier: Operating System :: OS Independent
Classifier: Programming Language :: Python :: 3
Classifier: Programming Language :: Python :: 3.9
Classifier: Programming Language :: Python :: 3.10
Classifier: Programming Language :: Python :: 3.11
Classifier: Programming Language :: Python :: 3.12
Classifier: Programming Language :: Python :: 3.13
Classifier: Topic :: Scientific/Engineering
Requires-Python: >=3.8
License-File: LICENSE
Requires-Dist: scipy
Requires-Dist: pandas
Requires-Dist: numpy
Requires-Dist: matplotlib
Requires-Dist: lmfit
Requires-Dist: setuptools
Requires-Dist: ncrystal
Requires-Dist: tqdm
Requires-Dist: joblib
Provides-Extra: dev
Requires-Dist: pytest>=6; extra == "dev"
Requires-Dist: pytest-cov>=3; extra == "dev"
Requires-Dist: pre-commit; extra == "dev"
Dynamic: license-file
